[ { "username": "ScubaSteve", "image": "trunkfish.JPG", "caption": "Some really cool caption about the fish I saw while scuba diving.", "location": "Bonaire",
    "comments": ["Great job", "Cool fish"]  },
    { "username": "ScubaSally", "image": "parrotfish.JPG", "caption": "Some really cool caption about the fish I saw while scuba diving.", "location": "Bonaire",
    "comments": ["Great job", "Cool fish"]  },
    { "username": "ScubaSam", "image": "tarpin.JPG", "caption": "Some really cool caption about the fish I saw while scuba diving.", "location": "Bonaire",
    "comments": ["Great job", "Cool fish"]  } ]